joltml/VERSION
joltml/__init__.py
joltml/__main__.py
joltml/cli.py
joltml/experiment.py
joltml/fit.py
joltml/joltmeter.py
joltml/joltml.py
joltml/status.py
joltml/version.py
joltml/model/__init__.py
joltml/model/keras.py
joltml/model/pytorch.py
joltml/model/sklearn.py
joltml/model/statsmodel.py
joltml/model/xgboost.py
joltml-0.1.3.dist-info/LICENSE
joltml-0.1.3.dist-info/METADATA
joltml-0.1.3.dist-info/WHEEL
joltml-0.1.3.dist-info/entry_points.txt
joltml-0.1.3.dist-info/top_level.txt
joltml-0.1.3.dist-info/RECORD
