Metadata-Version: 2.1
Name: joltml
Version: 0.1.3
Summary: joltml unravels the dark side of machine learning models
Home-page: https://github.com/sheriftawfikabbas/joltml
Author: Sherif Abdulkader Tawfik Abbas
Author-email: sherif.tawfic@gmail.com
License: mit
Keywords: ai,machine learning,machine learning workflowmodel tracking
License-File: LICENSE
Requires-Dist: xgboost
Requires-Dist: pandas
Requires-Dist: numpy
Requires-Dist: torch
Requires-Dist: tensorflow
Requires-Dist: scikit-learn
Requires-Dist: captum
Requires-Dist: optuna
